Metadata-Version: 2.1
Name: video-pipeline
Version: 0.0.2
Summary: Simplify the video streaming pipeline to provide frame by frame image manipulation in near real-time.
Home-page: https://github.com/Nate-Wilkins/video-pipeline
Author: Nate Wilkins, Phil Linden
Author-email: nate-wilkins@code-null.com, lindenphilipj@gmail.com
License: LICENSE
Project-URL: Source, https://github.com/Nate-Wilkins/video-pipeline
Project-URL: Changelog, https://github.com/Nate-Wilkins/video-pipeline/releases
Project-URL: Documentation, https://video-pipeline.readthedocs.io/
Keywords: video pipeline filter visualization multiprocessing
Platform: UNKNOWN
Classifier: License :: OSI Approved :: GNU Affero General Public License v3
Classifier: Intended Audience :: Developers
Classifier: Natural Language :: English
Classifier: Topic :: Multimedia :: Video
Classifier: Topic :: Multimedia :: Video :: Capture
Classifier: Topic :: Scientific/Engineering
Classifier: Topic :: Scientific/Engineering :: Visualization
Classifier: Programming Language :: Python :: 3.7
